pytest_adf/__init__.py
pytest_adf/pytest_adf.py
pytest_adf_azure_identity-0.0.1.dist-info/LICENSE
pytest_adf_azure_identity-0.0.1.dist-info/METADATA
pytest_adf_azure_identity-0.0.1.dist-info/WHEEL
pytest_adf_azure_identity-0.0.1.dist-info/entry_points.txt
pytest_adf_azure_identity-0.0.1.dist-info/top_level.txt
pytest_adf_azure_identity-0.0.1.dist-info/RECORD
