Metadata-Version: 2.1
Name: pytest-adf-azure-identity
Version: 0.0.1
Summary: Pytest plugin for writing Azure Data Factory integration tests
Home-page: https://github.com/mdrakiburrahman/pytest-adf-azure-identity
Author: Raki Rahman
Author-email: mdrakiburrahman@gmail.com
Maintainer: Raki Rahman
Maintainer-email: mdrakiburrahman@gmail.com
License: MIT
Platform: UNKNOWN
Classifier: Development Status :: 4 - Beta
Classifier: Framework :: Pytest
Classifier: Intended Audience :: Developers
Classifier: Topic :: Software Development :: Testing
Classifier: Programming Language :: Python
Classifier: Programming Language :: Python :: 3
Classifier: Programming Language :: Python :: 3.5
Classifier: Programming Language :: Python :: 3.6
Classifier: Programming Language :: Python :: 3.7
Classifier: Programming Language :: Python :: Implementation :: CPython
Classifier: Programming Language :: Python :: Implementation :: PyPy
Classifier: Operating System :: OS Independent
Classifier: License :: OSI Approved :: MIT License
Requires-Python: >=3.5
Requires-Dist: pytest (>=3.5.0)
